{"SyJaynes":{"player_code_id":{"code":"SyJaynes","id":"Jaynes, Sydney","ncaa_id":"4899006"},"number":"32","pos":"F","height":"6-3","height_in":75,"year_class":"Sr","gp":34,"origin":"Brownstown, IN"},"LiCarmody":{"player_code_id":{"code":"LiCarmody","id":"Carmody, Lily","ncaa_id":"5240218"},"number":"12","pos":"G","height":"5-11","height_in":71,"year_class":"Fr","gp":31,"origin":"Melbourne, Australia"},"LiZeinstra":{"player_code_id":{"code":"LiZeinstra","id":"Zeinstra, Lily","ncaa_id":"5240217"},"number":"10","pos":"G","height":"5-11","height_in":71,"year_class":"Fr","gp":34,"origin":"Byron Center, MI"},"JoMeulemans":{"player_code_id":{"code":"JoMeulemans","id":"Meulemans, Jordan","ncaa_id":"5106177"},"number":"23","pos":"G","height":"6-0","height_in":72,"year_class":"Jr","gp":0,"origin":"De Pere, WI"},"CaStrande":{"player_code_id":{"code":"CaStrande","id":"Strande, Caroline","ncaa_id":"4596310"},"number":"21","pos":"G","height":"5-11","height_in":71,"year_class":"Sr","gp":13,"origin":"Racine, WI"},"KaNorman":{"player_code_id":{"code":"KaNorman","id":"Norman, Karsyn","ncaa_id":"5175045"},"number":"1","pos":"G","height":"5-6","height_in":66,"year_class":"So","gp":32,"origin":"Bedford, IN"},"McSwanson":{"player_code_id":{"code":"McSwanson","id":"Swanson, Mckenzie","ncaa_id":"5240216"},"number":"5","pos":"F","height":"6-3","height_in":75,"year_class":"Fr","gp":0,"origin":"Rochester, MI"},"__coach__":{"player_code_id":{"code":"__coach__","id":"Austin Parkinson"},"number":"","pos":"","height":"","year_class":"","gp":-1},"LiStoddard":{"player_code_id":{"code":"LiStoddard","id":"Stoddard, Lilly","ncaa_id":"4698731"},"number":"31","pos":"F","height":"6-4","height_in":76,"year_class":"Jr","gp":24,"origin":"Crown Point, IN"},"ArWiggins":{"player_code_id":{"code":"ArWiggins","id":"Wiggins, Ari","ncaa_id":"4433522"},"number":"3","pos":"G","height":"5-8","height_in":68,"year_class":"Sr","gp":33,"origin":"Indianapolis, IN"},"KiMcguff":{"player_code_id":{"code":"KiMcguff","id":"McGuff, Kilyn","ncaa_id":"4900196"},"number":"11","pos":"G","height":"6-0","height_in":72,"year_class":"Sr","gp":34,"origin":"Columbus, OH"},"JoLand":{"player_code_id":{"code":"JoLand","id":"Land, Jocelyn","ncaa_id":"5240219"},"number":"14","pos":"F","height":"6-0","height_in":72,"year_class":"Fr","gp":32,"origin":"Chanhassen, MN"},"CrCarter":{"player_code_id":{"code":"CrCarter","id":"Carter, Cristen","ncaa_id":"5175047"},"number":"24","pos":"F","height":"6-4","height_in":76,"year_class":"So","gp":32,"origin":"Indianapolis, IN"},"RiMakalusky":{"player_code_id":{"code":"RiMakalusky","id":"Makalusky, Riley","ncaa_id":"5175046"},"number":"2","pos":"G","height":"6-2","height_in":74,"year_class":"So","gp":32,"origin":"Fishers, IN"}}