{"KeDudley":{"player_code_id":{"code":"KeDudley","id":"Dudley, Kendall","ncaa_id":"5239705"},"number":"22","pos":"F","height":"6-2","height_in":74,"year_class":"Fr","gp":37,"origin":"Manassas Park, VA"},"ZaSocka-ngue":{"player_code_id":{"code":"ZaSocka-ngue","id":"Socka-Nguemen, Zania","ncaa_id":"5239703"},"number":"6","pos":"F","height":"6-3","height_in":75,"year_class":"Fr","gp":16,"origin":"Manassas Park, VA"},"ElAarnisalo":{"player_code_id":{"code":"ElAarnisalo","id":"Aarnisalo, Elina","ncaa_id":"5239704"},"number":"7","pos":"G","height":"5-10","height_in":70,"year_class":"Fr","gp":37,"origin":"Helsinki, Finland"},"LaBetts":{"player_code_id":{"code":"LaBetts","id":"Betts, Lauren","ncaa_id":"5105737"},"number":"51","pos":"C","height":"6-7","height_in":79,"year_class":"Jr","gp":34,"origin":"Centennial, CO"},"AnDugalic":{"player_code_id":{"code":"AnDugalic","id":"Dugalic, Angela","ncaa_id":"4433411"},"number":"32","pos":"F","height":"6-4","height_in":76,"year_class":"Sr","gp":35,"origin":"Des Plaines, IL"},"AmMuse":{"player_code_id":{"code":"AmMuse","id":"Muse, Amanda","ncaa_id":"5175937"},"number":"33","pos":"F","height":"6-4","height_in":76,"year_class":"So","gp":0,"origin":"Brentwood, CA"},"__coach__":{"player_code_id":{"code":"__coach__","id":"Cori Close"},"number":"","pos":"","height":"","year_class":"","gp":-1},"GaJaquez":{"player_code_id":{"code":"GaJaquez","id":"Jaquez, Gabriela","ncaa_id":"4858656"},"number":"11","pos":"F","height":"6-0","height_in":72,"year_class":"Jr","gp":36,"origin":"Camarillo, CA"},"ChLeger-walk":{"player_code_id":{"code":"ChLeger-walk","id":"Leger-Walker, Charlisse","ncaa_id":"5239702"},"number":"5","pos":"G","height":"5-10","height_in":70,"year_class":"Sr","gp":0,"origin":"Hamilton, New Zealand"},"KiRice":{"player_code_id":{"code":"KiRice","id":"Rice, Kiki","ncaa_id":"4565505"},"number":"1","pos":"G","height":"5-11","height_in":71,"year_class":"Jr","gp":34,"origin":"Bethesda, MD"},"AvCain":{"player_code_id":{"code":"AvCain","id":"Cain, Avary","ncaa_id":"5239701"},"number":"2","pos":"G","height":"6-1","height_in":73,"year_class":"Fr","gp":18,"origin":"Santa Maria, CA"},"TiGardiner":{"player_code_id":{"code":"TiGardiner","id":"Gardiner, Timea","ncaa_id":"5105734"},"number":"30","pos":"F","height":"6-3","height_in":75,"year_class":"So","gp":36,"origin":"Ogden, UT"},"LoJones":{"player_code_id":{"code":"LoJones","id":"Jones, Londynn","ncaa_id":"4565506"},"number":"3","pos":"G","height":"5-4","height_in":64,"year_class":"Jr","gp":37,"origin":"Riverside, CA"},"JaBarker":{"player_code_id":{"code":"JaBarker","id":"Barker, Janiah","ncaa_id":"5239700"},"number":"0","pos":"F","height":"6-4","height_in":76,"year_class":"Jr","gp":36,"origin":"Marietta, GA"}}