{"TrYoung":{"player_code_id":{"code":"TrYoung","id":"Young, Trace","ncaa_id":"4703222"},"number":"0","pos":"G","height":"6-4","height_in":76,"year_class":"Jr","gp":12,"origin":"Austin, TX","lat":30.2711286,"lon":-97.7436995},"LuMurphy":{"player_code_id":{"code":"LuMurphy","id":"Murphy, Luke","ncaa_id":"5107565"},"number":"14","pos":"G","height":"5-11","height_in":71,"year_class":"Fr","gp":0,"origin":"Calabasas, CA","lat":34.1446643,"lon":-118.644097},"JaMoors":{"player_code_id":{"code":"JaMoors","id":"Moors, James","ncaa_id":"4593039"},"number":"10","pos":"F","height":"6-10","height_in":82,"year_class":"Jr","gp":33,"origin":"Auckland, New Zealand"},"PaCartier":{"player_code_id":{"code":"PaCartier","id":"Cartier, Patrick","ncaa_id":"5107564"},"number":"12","pos":"F","height":"6-8","height_in":80,"year_class":"Jr","gp":33,"origin":"Brookfield, WI","lat":43.0615578,"lon":-88.1260678},"JoPalmer":{"player_code_id":{"code":"JoPalmer","id":"Palmer, Joe","ncaa_id":"5107566"},"number":"20","pos":"G","height":"6-4","height_in":76,"year_class":"Sr","gp":33,"origin":"Faribault, MN","lat":44.2949637,"lon":-93.268827},"JaPayne":{"player_code_id":{"code":"JaPayne","id":"Payne, Jack","ncaa_id":"5107563"},"number":"11","pos":"G","height":"6-6","height_in":78,"year_class":"Fr","gp":0,"origin":"Boise, ID","lat":43.6166163,"lon":-116.200886},"IsRivera":{"player_code_id":{"code":"IsRivera","id":"Rivera, Isaiah","ncaa_id":"4703224"},"number":"23","pos":"G","height":"6-5","height_in":77,"year_class":"Jr","gp":33,"origin":"Geneseo, IL","lat":41.4525168,"lon":-90.1548364},"__coach__":{"player_code_id":{"code":"__coach__","id":"Niko Medved"},"number":"","pos":"","height":"","year_class":"","gp":-1},"TaJackson":{"player_code_id":{"code":"TaJackson","id":"Jackson, Tavi","ncaa_id":"5107562"},"number":"2","pos":"G","height":"6-2","height_in":74,"year_class":"Fr","gp":28,"origin":"Las Vegas, NV","lat":36.1672559,"lon":-115.148516},"JoTonje":{"player_code_id":{"code":"JoTonje","id":"Tonje, John","ncaa_id":"4593043"},"number":"1","pos":"G","height":"6-5","height_in":77,"year_class":"Sr","gp":33,"origin":"Omaha, NE","lat":41.2587459,"lon":-95.9383758},"IsStevens":{"player_code_id":{"code":"IsStevens","id":"Stevens, Isaiah","ncaa_id":"4432117"},"number":"4","pos":"G","height":"6-0","height_in":72,"year_class":"Sr","gp":26,"origin":"Allen, TX","lat":33.1031744,"lon":-96.6705503},"BaHebb":{"player_code_id":{"code":"BaHebb","id":"Hebb, Baylor","ncaa_id":"4585600"},"number":"5","pos":"G","height":"6-2","height_in":74,"year_class":"Jr","gp":33,"origin":"Colleyville, TX","lat":32.8809603,"lon":-97.155012},"KyEvans":{"player_code_id":{"code":"KyEvans","id":"Evans, Kyle","ncaa_id":"5107567"},"number":"32","pos":"F","height":"6-10","height_in":82,"year_class":"Fr","gp":11,"origin":"Aliso Viejo, CA","lat":33.5761376,"lon":-117.7258122},"JaJennissen":{"player_code_id":{"code":"JaJennissen","id":"Jennissen, Jacob","ncaa_id":"4703225"},"number":"35","pos":"C","height":"7-1","height_in":85,"year_class":"Jr","gp":0,"origin":"Sauk Centre, MN","lat":45.737465,"lon":-94.9525216},"NiBassett":{"player_code_id":{"code":"NiBassett","id":"Bassett, Nick","ncaa_id":"4703223"},"number":"22","pos":"F","height":"6-5","height_in":77,"year_class":"Sr","gp":1,"origin":"Colorado Springs, CO","lat":38.8339578,"lon":-104.825348},"JaLake":{"player_code_id":{"code":"JaLake","id":"Lake, Jalen","ncaa_id":"4897514"},"number":"15","pos":"G","height":"6-4","height_in":76,"year_class":"So","gp":26,"origin":"Waxahachie, TX","lat":32.3944908,"lon":-96.8439365},"JoStrong":{"player_code_id":{"code":"JoStrong","id":"Strong, Josiah","ncaa_id":"4398146"},"number":"3","pos":"G","height":"6-4","height_in":76,"year_class":"Sr","gp":7,"origin":"Brooklyn Park, MN","lat":45.1004807,"lon":-93.3443585}}