{"LeWatts":{"player_code_id":{"code":"LeWatts","id":"Watts, LeJuan","ncaa_id":"8177727"},"number":"4","pos":"F","height":"6-6","height_in":78,"year_class":"Fr","gp":0,"origin":"Fresno, CA"},"AmSavage":{"player_code_id":{"code":"AmSavage","id":"Savage, Amarion","ncaa_id":"8392613"},"number":"14","pos":"G","height":"6-0","height_in":72,"year_class":"Fr","gp":0,"origin":"Aurora, IL"},"__coach__":{"player_code_id":{"code":"__coach__","id":"David Riley"},"number":"","pos":"","height":"","year_class":"","gp":-1},"TyHarper":{"player_code_id":{"code":"TyHarper","id":"Harper, Ty","ncaa_id":"7077837"},"number":"11","pos":"G","height":"6-3","height_in":75,"year_class":"So","gp":20,"origin":"Norcross, GA"},"ImGeorge":{"player_code_id":{"code":"ImGeorge","id":"George, Imhotep","ncaa_id":"7479900"},"number":"25","pos":"F","height":"6-8","height_in":80,"year_class":"Jr","gp":7,"origin":"Laurel, MD"},"JoVeening":{"player_code_id":{"code":"JoVeening","id":"Veening, Jordan","ncaa_id":"5983211"},"number":"23","pos":"F","height":"6-6","height_in":78,"year_class":"Sr","gp":7,"origin":"Sumas, WA"},"DaErikstrup":{"player_code_id":{"code":"DaErikstrup","id":"Erikstrup, Dane","ncaa_id":"7492026"},"number":"32","pos":"F","height":"6-11","height_in":83,"year_class":"So","gp":34,"origin":"Beaverton, OR"},"SeAndersson":{"player_code_id":{"code":"SeAndersson","id":"Andersson, Sebastian","ncaa_id":"8306805"},"number":"34","pos":"F","height":"6-10","height_in":82,"year_class":"Fr","gp":0,"origin":"Stockholm, Sweden"},"CeCoward":{"player_code_id":{"code":"CeCoward","id":"Coward, Cedric","ncaa_id":"7524232"},"number":"0","pos":"F","height":"6-6","height_in":78,"year_class":"So","gp":34,"origin":"Fresno, CA"},"EtPrice":{"player_code_id":{"code":"EtPrice","id":"Price, Ethan","ncaa_id":"7479867"},"number":"10","pos":"F","height":"6-10","height_in":82,"year_class":"So","gp":34,"origin":"Bury St Edmunds, United Kingdom"},"DeStroud":{"player_code_id":{"code":"DeStroud","id":"Stroud, Deon","ncaa_id":"6384731"},"number":"5","pos":"G","height":"6-5","height_in":77,"year_class":"Sr","gp":33,"origin":"Fresno, CA"},"StVenters":{"player_code_id":{"code":"StVenters","id":"Venters, Steele","ncaa_id":"6836771"},"number":"2","pos":"F","height":"6-7","height_in":79,"year_class":"So","gp":34,"origin":"Ellensburg, WA"},"ElMagnuson":{"player_code_id":{"code":"ElMagnuson","id":"Magnuson, Ellis","ncaa_id":"6483729"},"number":"55","pos":"G","height":"6-1","height_in":73,"year_class":"Jr","gp":28,"origin":"Boise, ID"},"AnAllegri":{"player_code_id":{"code":"AnAllegri","id":"Allegri, Angelo","ncaa_id":"5993333"},"number":"13","pos":"F","height":"6-7","height_in":79,"year_class":"Sr","gp":34,"origin":"Kansas City, MO"},"TyDavis":{"player_code_id":{"code":"TyDavis","id":"Davis, Tyreese","ncaa_id":"5985525"},"number":"1","pos":"G","height":"6-6","height_in":78,"year_class":"Jr","gp":31,"origin":"Kansas City, MO"},"CaJones":{"player_code_id":{"code":"CaJones","id":"Jones, Casey","ncaa_id":"7479902"},"number":"31","pos":"F","height":"6-6","height_in":78,"year_class":"So","gp":33,"origin":"Sammamish, WA"}}
