{"ThWeaver":{"player_code_id":{"code":"ThWeaver","id":"Weaver, Thomas","ncaa_id":"4704042"},"number":"13","pos":"G","height":"5-10","height_in":70,"year_class":"Fr","gp":5,"origin":"Upper Marlboro, MD","lat":38.8162451,"lon":-76.751708},"StSettle":{"player_code_id":{"code":"StSettle","id":"Settle, Steve","ncaa_id":"4704043"},"number":"2","pos":"F","height":"6-10","height_in":82,"year_class":"Fr","gp":5,"origin":"Glenarden, MD","lat":38.9292782,"lon":-76.8616387},"SpHayes":{"player_code_id":{"code":"SpHayes","id":"Hayes, Spencer","ncaa_id":"4704046"},"number":"14","pos":"G","height":"6-5","height_in":77,"year_class":"Fr","gp":3,"origin":"Upper Marlboro, MD","lat":38.8162451,"lon":-76.751708},"NoEastern":{"player_code_id":{"code":"NoEastern","id":"Eastern, Nojel","ncaa_id":"4277984"},"number":"20","pos":"G","height":"6-7","height_in":79,"year_class":"Sr","gp":0,"origin":"Evanston, IL","lat":42.0470043,"lon":-87.6846053},"KyFoster":{"player_code_id":{"code":"KyFoster","id":"Foster, Kyle","ncaa_id":"4279792"},"number":"11","pos":"G","height":"6-6","height_in":78,"year_class":"Sr","gp":4,"origin":"Hampton, VA","lat":37.0264414,"lon":-76.3442846},"MaMaker":{"player_code_id":{"code":"MaMaker","id":"Maker, Makur","ncaa_id":"4432183"},"number":"4","pos":"C","height":"6-11","height_in":83,"year_class":"Fr","gp":2,"origin":"West Hills, CA","lat":34.2032325,"lon":-118.645476},"WaBristol":{"player_code_id":{"code":"WaBristol","id":"Bristol, Jr., Wayne","ncaa_id":"4593375"},"number":"31","pos":"G","height":"6-6","height_in":78,"year_class":"So","gp":0,"origin":"Upper Marlboro, MD","lat":38.8162451,"lon":-76.751708},"KhRobinson":{"player_code_id":{"code":"KhRobinson","id":"Robinson, Khalil","ncaa_id":"4432102"},"number":"0","pos":"G","height":"5-11","height_in":71,"year_class":"So","gp":5,"origin":"Columbia, SC","lat":34.000754,"lon":-81.0352313},"ChJohnson":{"player_code_id":{"code":"ChJohnson","id":"Johnson, Christian","ncaa_id":"4704047"},"number":"21","pos":"F","height":"6-7","height_in":79,"year_class":"Fr","gp":0,"origin":"Washington, DC","lat":38.8950368,"lon":-77.0365427},"RaAli":{"player_code_id":{"code":"RaAli","id":"Ali, Jr., Rahim","ncaa_id":"4704045"},"number":"1","pos":"G","height":"5-11","height_in":71,"year_class":"Fr","gp":4,"origin":"Baltimore, MD","lat":39.2908816,"lon":-76.610759},"JoWood":{"player_code_id":{"code":"JoWood","id":"Wood, Jordan","ncaa_id":"4704048"},"number":"24","pos":"F","height":"6-9","height_in":81,"year_class":"Fr","gp":3,"origin":"San Antonio, TX","lat":29.4246002,"lon":-98.4951405},"IsSuffren":{"player_code_id":{"code":"IsSuffren","id":"Suffren, Isaac","ncaa_id":"4398072"},"number":"15","pos":"G","height":"6-4","height_in":76,"year_class":"So","gp":5,"origin":"Charlotte, NC","lat":35.2272086,"lon":-80.8430827},"CaTimmons":{"player_code_id":{"code":"CaTimmons","id":"Timmons, Cam","ncaa_id":"4593374"},"number":"22","pos":"C","height":"6-11","height_in":83,"year_class":"So","gp":5,"origin":"Warrenton, VA","lat":38.7135498,"lon":-77.795367},"SaGreen":{"player_code_id":{"code":"SaGreen","id":"Green, Sam","ncaa_id":"4067227"},"number":"5","pos":"F","height":"6-6","height_in":78,"year_class":"Sr","gp":5,"origin":"Bowie, MD","lat":38.9424464,"lon":-76.7301718},"DeRichmond":{"player_code_id":{"code":"DeRichmond","id":"Richmond, Deven","ncaa_id":"4704044"},"number":"10","pos":"G","height":"6-4","height_in":76,"year_class":"Jr","gp":5,"origin":"Washington, DC","lat":38.8950368,"lon":-77.0365427},"LiRichardson":{"player_code_id":{"code":"LiRichardson","id":"Richardson, Liwayne","ncaa_id":"4593376"},"number":"32","pos":"C","height":"6-10","height_in":82,"year_class":"So","gp":5,"origin":"The Valley, Anguilla"}}