{"JaKukic":{"player_code_id":{"code":"JaKukic","id":"Kukic, Jakov","ncaa_id":"4431850"},"number":"14","pos":"F","height":"6-10","height_in":82,"year_class":"Fr","gp":14,"origin":"Split, Croatia"},"GaGomez":{"player_code_id":{"code":"GaGomez","id":"Gomez, Gage","ncaa_id":"4702594"},"number":"50","pos":"G","height":"6-3","height_in":75,"year_class":"Fr","gp":8,"origin":"Arroyo Grande, CA","lat":35.1235374,"lon":-120.5785796},"JoPierre-lou":{"player_code_id":{"code":"JoPierre-lou","id":"Pierre-Louis, Josh","ncaa_id":"4431795"},"number":"2","pos":"G","height":"6-3","height_in":75,"year_class":"So","gp":23,"origin":"Plainfield, NJ","lat":40.6201412,"lon":-74.4222416},"AmSow":{"player_code_id":{"code":"AmSow","id":"Sow, Amadou","ncaa_id":"4397644"},"number":"12","pos":"F","height":"6-9","height_in":81,"year_class":"Jr","gp":26,"origin":"Bamako, Mali"},"DeBarnes":{"player_code_id":{"code":"DeBarnes","id":"Barnes, Destin","ncaa_id":"4067100"},"number":"23","pos":"G","height":"6-7","height_in":79,"year_class":"Sr","gp":27,"origin":"Chicago, IL","lat":41.8755616,"lon":-87.6244212},"AjSanni":{"player_code_id":{"code":"AjSanni","id":"Sanni, Ajare","ncaa_id":"4397676"},"number":"13","pos":"G","height":"6-3","height_in":75,"year_class":"So","gp":25,"origin":"Houston, TX","lat":29.7589382,"lon":-95.3676974},"CaWishart":{"player_code_id":{"code":"CaWishart","id":"Wishart, Calvin","ncaa_id":"4397521"},"number":"10","pos":"","height":"-","year_class":"N/A","gp":0,"origin":"Delano, MN","lat":45.0419073,"lon":-93.7891331},"JaNagle":{"player_code_id":{"code":"JaNagle","id":"Nagle, Jay","ncaa_id":"4397643"},"number":"1","pos":"F","height":"6-8","height_in":80,"year_class":"Jr","gp":16,"origin":"Vacaville, CA","lat":38.3565773,"lon":-121.9877444},"MiNorris":{"player_code_id":{"code":"MiNorris","id":"Norris, Miles","ncaa_id":"4397104"},"number":"5","pos":"F","height":"6-10","height_in":82,"year_class":"Jr","gp":27,"origin":"San Diego, CA","lat":32.7174202,"lon":-117.162772},"DaLong":{"player_code_id":{"code":"DaLong","id":"Long, Darren","ncaa_id":"4592994"},"number":"55","pos":"G","height":"6-3","height_in":75,"year_class":"Fr","gp":0,"origin":"Altadena, CA","lat":34.1928193,"lon":-118.137466344567},"JaMclaughlin":{"player_code_id":{"code":"JaMclaughlin","id":"McLaughlin, Jaquori","ncaa_id":"4066496"},"number":"3","pos":"G","height":"6-4","height_in":76,"year_class":"Sr","gp":26,"origin":"Tacoma, WA","lat":47.2455013,"lon":-122.438329},"RoIdehen":{"player_code_id":{"code":"RoIdehen","id":"Idehen, Robinson","ncaa_id":"4397646"},"number":"24","pos":"F","height":"6-10","height_in":82,"year_class":"Sr","gp":27,"origin":"Tudela, Spain"},"SeToure":{"player_code_id":{"code":"SeToure","id":"Toure, Sekou","ncaa_id":"4397642"},"number":"0","pos":"G","height":"6-5","height_in":77,"year_class":"Jr","gp":17,"origin":"Conakry, Guinea"},"DeRamsey":{"player_code_id":{"code":"DeRamsey","id":"Ramsey, Devearl","ncaa_id":"4066700"},"number":"4","pos":"G","height":"6-0","height_in":72,"year_class":"Sr","gp":27,"origin":"Los Angeles, CA","lat":34.0536909,"lon":-118.242766},"BrCyrus":{"player_code_id":{"code":"BrCyrus","id":"Cyrus, Brandon","ncaa_id":"4065775"},"number":"11","pos":"G","height":"6-5","height_in":77,"year_class":"Sr","gp":27,"origin":"Oakville, ON","lat":40.0792119,"lon":-85.3905265},"MaCheylov":{"player_code_id":{"code":"MaCheylov","id":"Cheylov, Max","ncaa_id":"4592993"},"number":"15","pos":"G","height":"6-3","height_in":75,"year_class":"Fr","gp":0,"origin":"Toronto, ON","lat":39.75946455,"lon":-87.50111485527069},"NiRocak":{"player_code_id":{"code":"NiRocak","id":"Rocak, Niko","ncaa_id":"4702596"},"number":"54","pos":"F","height":"6-9","height_in":81,"year_class":"Fr","gp":2,"origin":"Geneva, Switzerland"},"KyMaclean":{"player_code_id":{"code":"KyMaclean","id":"MacLean, Kyle","ncaa_id":"4702595"},"number":"52","pos":"G","height":"6-2","height_in":74,"year_class":"Fr","gp":2,"origin":"Westlake Village, CA","lat":34.1460234,"lon":-118.8061794}}