{"KkRobinson":{"player_code_id":{"code":"KkRobinson","id":"Robinson, KK","ncaa_id":"7366380"},"number":"2","pos":"G","height":"6-0","height_in":72,"year_class":"So","gp":19,"origin":"Little Rock, AR"},"JaWilliams":{"player_code_id":{"code":"JaWilliams","id":"Williams, Jaylin","ncaa_id":"7366379"},"number":"10","pos":"F","height":"6-10","height_in":82,"year_class":"So","gp":37,"origin":"Fort Smith, AR"},"ChMoore":{"player_code_id":{"code":"ChMoore","id":"Moore, Chance","ncaa_id":"7480242"},"number":"13","pos":"G","height":"6-6","height_in":78,"year_class":"Fr","gp":5,"origin":"Brookhaven, GA"},"TrWade":{"player_code_id":{"code":"TrWade","id":"Wade, Trey","ncaa_id":"7480217"},"number":"3","pos":"F","height":"6-6","height_in":78,"year_class":"Sr","gp":37,"origin":"Marietta, GA"},"ChLykes":{"player_code_id":{"code":"ChLykes","id":"Lykes, Chris","ncaa_id":"7480225"},"number":"11","pos":"G","height":"5-7","height_in":67,"year_class":"Sr","gp":37,"origin":"Mitchellville, MD"},"__coach__":{"player_code_id":{"code":"__coach__","id":"Eric Musselman"},"number":"","pos":"","height":"","year_class":"","gp":-1},"CoVanover":{"player_code_id":{"code":"CoVanover","id":"Vanover, Connor","ncaa_id":"7366386"},"number":"23","pos":"F","height":"7-5","height_in":89,"year_class":"Jr","gp":15,"origin":"Little Rock, AR"},"AuToney":{"player_code_id":{"code":"AuToney","id":"Toney, Au'Diese","ncaa_id":"7480221"},"number":"5","pos":"G","height":"6-6","height_in":78,"year_class":"Sr","gp":36,"origin":"Huntsville, AL"},"DaDavis":{"player_code_id":{"code":"DaDavis","id":"Davis, Davonte","ncaa_id":"7366378"},"number":"4","pos":"G","height":"6-4","height_in":76,"year_class":"So","gp":37,"origin":"Jacksonville, AR"},"JaRobinson":{"player_code_id":{"code":"JaRobinson","id":"Robinson, Jaxson","ncaa_id":"7480227"},"number":"14","pos":"G","height":"6-6","height_in":78,"year_class":"So","gp":16,"origin":"Ada, OK"},"CaArbogast":{"player_code_id":{"code":"CaArbogast","id":"Arbogast, Cade","ncaa_id":"7480071"},"number":"21","pos":"G","height":"6-3","height_in":75,"year_class":"So","gp":4,"origin":"Concord, CA"},"LaBlake":{"player_code_id":{"code":"LaBlake","id":"Blake, Lawson","ncaa_id":"7480273"},"number":"45","pos":"F","height":"6-10","height_in":82,"year_class":"Fr","gp":5,"origin":"Fayetteville, AR"},"KaJohnson":{"player_code_id":{"code":"KaJohnson","id":"Johnson, Kamani","ncaa_id":"7480231"},"number":"20","pos":"F","height":"6-7","height_in":79,"year_class":"Jr","gp":26,"origin":"Brooklyn, NY"},"JdNotae":{"player_code_id":{"code":"JdNotae","id":"Notae, JD","ncaa_id":"7366385"},"number":"1","pos":"G","height":"6-2","height_in":74,"year_class":"Sr","gp":36,"origin":"Covington, GA"},"StUmude":{"player_code_id":{"code":"StUmude","id":"Umude, Stanley","ncaa_id":"7480214"},"number":"0","pos":"G","height":"6-6","height_in":78,"year_class":"Sr","gp":37,"origin":"San Antonio, TX"}}
