{"JaPal":{"player_code_id":{"code":"JaPal","id":"Pal, Jay","ncaa_id":"4703247"},"number":"13","pos":"G","height":"6-9","height_in":81,"year_class":"So","gp":28,"origin":"Omaha, NE","lat":41.2587459,"lon":-95.9383758},"DeKing":{"player_code_id":{"code":"DeKing","id":"King, Demaree","ncaa_id":"4703244"},"number":"1","pos":"G","height":"6-0","height_in":72,"year_class":"Jr","gp":32,"origin":"Tulsa, OK","lat":36.1563122,"lon":-95.9927516},"CaByrd":{"player_code_id":{"code":"CaByrd","id":"Byrd, Caleb","ncaa_id":"4702737"},"number":"5","pos":"G","height":"6-1","height_in":73,"year_class":"Fr","gp":14,"origin":"Atlanta, GA","lat":33.7489924,"lon":-84.3902644},"MaBrigham":{"player_code_id":{"code":"MaBrigham","id":"Brigham Jr, Marcellus","ncaa_id":"4703246"},"number":"4","pos":"F","height":"6-7","height_in":79,"year_class":"Fr","gp":12,"origin":"Memphis, TN","lat":35.1460249,"lon":-90.0517638},"BrHuffman":{"player_code_id":{"code":"BrHuffman","id":"Huffman, Brandon","ncaa_id":"4277912"},"number":"50","pos":"C","height":"6-10","height_in":82,"year_class":"Sr","gp":32,"origin":"Goldsboro, NC","lat":35.3848841,"lon":-77.9927651},"JaGibbs":{"player_code_id":{"code":"JaGibbs","id":"Gibbs, Jalen","ncaa_id":"4278993"},"number":"22","pos":"G","height":"6-3","height_in":75,"year_class":"Sr","gp":32,"origin":"Indian Head, MD","lat":38.5997628,"lon":-77.1647714},"__coach__":{"player_code_id":{"code":"__coach__","id":"Ray Harper"},"number":"","pos":"","height":"","year_class":"","gp":-1},"TaTouze":{"player_code_id":{"code":"TaTouze","id":"Touze, Tanguy","ncaa_id":"4898253"},"number":"20","pos":"G","height":"6-3","height_in":75,"year_class":"Fr","gp":7,"origin":"Pontault-Combault, France"},"KaHenry":{"player_code_id":{"code":"KaHenry","id":"Henry, Kayne","ncaa_id":"4593671"},"number":"11","pos":"F","height":"6-7","height_in":79,"year_class":"Sr","gp":32,"origin":"London, England"},"JjPlatt":{"player_code_id":{"code":"JjPlatt","id":"Platt, JJ","ncaa_id":"4703248"},"number":"15","pos":"G","height":"6-1","height_in":73,"year_class":"Fr","gp":0,"origin":"Nashville, TN","lat":36.1622767,"lon":-86.7742984},"AmNgumezi":{"player_code_id":{"code":"AmNgumezi","id":"Ngumezi, Amanze","ncaa_id":"4395720"},"number":"24","pos":"F","height":"6-9","height_in":81,"year_class":"Sr","gp":0,"origin":"Savannah, GA","lat":32.0790074,"lon":-81.0921335},"JaFinch":{"player_code_id":{"code":"JaFinch","id":"Finch, Jalen","ncaa_id":"4703243"},"number":"0","pos":"G","height":"6-1","height_in":73,"year_class":"Jr","gp":31,"origin":"Raleigh, NC","lat":35.7803977,"lon":-78.6390989},"JuPerdue":{"player_code_id":{"code":"JuPerdue","id":"Perdue, Juwan","ncaa_id":"4433059"},"number":"10","pos":"F","height":"6-6","height_in":78,"year_class":"So","gp":31,"origin":"Sumter, SC","lat":33.9204354,"lon":-80.3414693},"SeHenderson":{"player_code_id":{"code":"SeHenderson","id":"Henderson, Semaj","ncaa_id":"4703245"},"number":"2","pos":"G","height":"6-2","height_in":74,"year_class":"Fr","gp":15,"origin":"Chicago, IL","lat":41.8755616,"lon":-87.6244212},"MaZeliznak":{"player_code_id":{"code":"MaZeliznak","id":"Zeliznak, Maros","ncaa_id":"4398323"},"number":"3","pos":"C","height":"6-11","height_in":83,"year_class":"Jr","gp":32,"origin":"Kosice, Slovakia"},"CaPope":{"player_code_id":{"code":"CaPope","id":"Pope, Cam","ncaa_id":"4898254"},"number":"55","pos":"G","height":"6-1","height_in":73,"year_class":"Fr","gp":0,"origin":"Louisville, KY","lat":38.2542376,"lon":-85.759407},"DaAdams":{"player_code_id":{"code":"DaAdams","id":"Adams, Darian","ncaa_id":"4067814"},"number":"23","pos":"G","height":"6-3","height_in":75,"year_class":"Sr","gp":31,"origin":"Montgomery, AK","lat":32.37742,"lon":-86.3091683}}