{"JaPierre":{"player_code_id":{"code":"JaPierre","id":"Pierre Jr., Jaron","ncaa_id":"4703115"},"number":"55","pos":"G","height":"6-6","height_in":78,"year_class":"Fr","gp":27,"origin":"New Orleans, LA","lat":29.9759983,"lon":-90.0782127},"JeArmstrong":{"player_code_id":{"code":"JeArmstrong","id":"Armstrong, Jeffery","ncaa_id":"4593269"},"number":"22","pos":"G","height":"6-0","height_in":72,"year_class":"Fr","gp":24,"origin":"Rainsville, AL","lat":34.4942536,"lon":-85.8477494},"TyStevenson":{"player_code_id":{"code":"TyStevenson","id":"Stevenson, Tyler","ncaa_id":"4397707"},"number":"14","pos":"F","height":"6-8","height_in":80,"year_class":"Jr","gp":28,"origin":"Columbus, MS","lat":33.4956744,"lon":-88.4272627},"TaHardy":{"player_code_id":{"code":"TaHardy","id":"Hardy, Tae","ncaa_id":"4396616"},"number":"10","pos":"G","height":"6-3","height_in":75,"year_class":"Jr","gp":7,"origin":"Ellenwood, GA","lat":33.6101096,"lon":-84.287978},"DeHarris":{"player_code_id":{"code":"DeHarris","id":"Harris, Denijay","ncaa_id":"4593268"},"number":"2","pos":"F","height":"6-7","height_in":79,"year_class":"Jr","gp":32,"origin":"Columbus, MS","lat":33.4956744,"lon":-88.4272627},"__coach__":{"player_code_id":{"code":"__coach__","id":"Jay Ladner"},"number":"","pos":"","height":"","year_class":"","gp":-1},"RaBolden":{"player_code_id":{"code":"RaBolden","id":"Bolden, Rashad","ncaa_id":"4897558"},"number":"4","pos":"G","height":"6-0","height_in":72,"year_class":"Fr","gp":33,"origin":"Jackson, MS","lat":32.2998686,"lon":-90.1830408},"IsMoore":{"player_code_id":{"code":"IsMoore","id":"Moore, Isaih","ncaa_id":"4397384"},"number":"11","pos":"F","height":"6-10","height_in":82,"year_class":"Jr","gp":27,"origin":"Columbia, SC","lat":34.000754,"lon":-81.0352313},"MoArnold":{"player_code_id":{"code":"MoArnold","id":"Arnold, Mo","ncaa_id":"4592260"},"number":"12","pos":"G","height":"6-1","height_in":73,"year_class":"So","gp":27,"origin":"Picayune, MS","lat":30.5254692,"lon":-89.6795084},"WaNapper":{"player_code_id":{"code":"WaNapper","id":"Napper, Walyn","ncaa_id":"4897557"},"number":"1","pos":"G","height":"6-1","height_in":73,"year_class":"So","gp":33,"origin":"Columbia, SC","lat":34.000754,"lon":-81.0352313},"DePinckney":{"player_code_id":{"code":"DePinckney","id":"Pinckney, DeAndre","ncaa_id":"4703112"},"number":"5","pos":"F","height":"6-8","height_in":80,"year_class":"Jr","gp":33,"origin":"Carol City, FL","lat":25.9406488,"lon":-80.2456045},"TrAlfonso":{"player_code_id":{"code":"TrAlfonso","id":"Alfonso, Trey","ncaa_id":"4897559"},"number":"21","pos":"G","height":"6-1","height_in":73,"year_class":"Fr","gp":8,"origin":"Chalmette, LA","lat":29.9427892,"lon":-89.9629372},"BlRoberts":{"player_code_id":{"code":"BlRoberts","id":"Roberts, Blake","ncaa_id":"4703111"},"number":"3","pos":"G","height":"6-2","height_in":74,"year_class":"So","gp":12,"origin":"Hattiesburg, MS","lat":31.3271189,"lon":-89.2903392},"MaJaakson":{"player_code_id":{"code":"MaJaakson","id":"Jaakson, Mark","ncaa_id":"4703114"},"number":"44","pos":"G","height":"6-7","height_in":79,"year_class":"Fr","gp":12,"origin":"Tallinn, Estonia"},"TaRyder":{"player_code_id":{"code":"TaRyder","id":"Ryder, Tate","ncaa_id":"4897560"},"number":"25","pos":"G","height":"6-0","height_in":72,"year_class":"So","gp":12,"origin":"Hattiesburg, MS","lat":32.6743017,"lon":-88.5644854},"TyMorman":{"player_code_id":{"code":"TyMorman","id":"Morman, Tyler","ncaa_id":"4593131"},"number":"0","pos":"F","height":"6-8","height_in":80,"year_class":"Jr","gp":26,"origin":"Mableton, GA","lat":33.8188333,"lon":-84.5822632}}