{"DeMahoney":{"player_code_id":{"code":"DeMahoney","id":"Mahoney, Denzel","ncaa_id":"4067205"},"number":"34","pos":"G","height":"6-4","height_in":76,"year_class":"Sr","gp":21,"origin":"Oviedo, FL","lat":28.6702526,"lon":-81.2084941},"MaZegarowski":{"player_code_id":{"code":"MaZegarowski","id":"Zegarowski, Marcus","ncaa_id":"4397036"},"number":"11","pos":"G","height":"6-2","height_in":74,"year_class":"So","gp":31,"origin":"Hamilton, MA","lat":42.6362052,"lon":-70.8431049},"MiBallock":{"player_code_id":{"code":"MiBallock","id":"Ballock, Mitch","ncaa_id":"4278556"},"number":"24","pos":"G","height":"6-5","height_in":77,"year_class":"Jr","gp":31,"origin":"Eudora, KS","lat":38.9433372,"lon":-95.0985808},"JaEpperson":{"player_code_id":{"code":"JaEpperson","id":"Epperson, Jacob","ncaa_id":"4278557"},"number":"41","pos":"C","height":"6-11","height_in":83,"year_class":"Jr","gp":0,"origin":"Melbourne, VIC"},"TyAlexander":{"player_code_id":{"code":"TyAlexander","id":"Alexander, Ty-Shon","ncaa_id":"4278555"},"number":"5","pos":"G","height":"6-4","height_in":76,"year_class":"Jr","gp":31,"origin":"Charlotte, NC","lat":35.2272086,"lon":-80.8430827},"JeCanfield":{"player_code_id":{"code":"JeCanfield","id":"Canfield, Jett","ncaa_id":"4397035"},"number":"10","pos":"G","height":"5-10","height_in":70,"year_class":"So","gp":21,"origin":"Topeka, KS","lat":39.049011,"lon":-95.677556},"JoScurry":{"player_code_id":{"code":"JoScurry","id":"Scurry, Jordan","ncaa_id":"4065767"},"number":"12","pos":"G","height":"6-2","height_in":74,"year_class":"Sr","gp":15,"origin":"Dedham, MA","lat":42.2489143,"lon":-71.1755732},"JaWindham":{"player_code_id":{"code":"JaWindham","id":"Windham, Jalen","ncaa_id":"4433123"},"number":"21","pos":"G","height":"6-5","height_in":77,"year_class":"Fr","gp":16,"origin":"Indianapolis, IN","lat":39.7683331,"lon":-86.1583502},"ShMitchell":{"player_code_id":{"code":"ShMitchell","id":"Mitchell, Shereef","ncaa_id":"4432059"},"number":"4","pos":"G","height":"6-0","height_in":72,"year_class":"Fr","gp":27,"origin":"Omaha, NE","lat":41.2587459,"lon":-95.9383758},"DaJefferson":{"player_code_id":{"code":"DaJefferson","id":"Jefferson, Damien","ncaa_id":"4066720"},"number":"23","pos":"G","height":"6-5","height_in":77,"year_class":"Jr","gp":30,"origin":"East Chicago, IN","lat":41.6397857,"lon":-87.4548466},"DaMintz":{"player_code_id":{"code":"DaMintz","id":"Mintz, Davion","ncaa_id":"4065766"},"number":"1","pos":"G","height":"6-3","height_in":75,"year_class":"Sr","gp":0,"origin":"Charlotte, NC","lat":35.2272086,"lon":-80.8430827},"NiZeil":{"player_code_id":{"code":"NiZeil","id":"Zeil, Nic","ncaa_id":"4592457"},"number":"20","pos":"F","height":"6-8","height_in":80,"year_class":"Fr","gp":15,"origin":"Kansas City, MO","lat":39.100105,"lon":-94.5781416},"ChBishop":{"player_code_id":{"code":"ChBishop","id":"Bishop, Christian","ncaa_id":"4397037"},"number":"13","pos":"F","height":"6-7","height_in":79,"year_class":"So","gp":31,"origin":"Lee's Summit, MO","lat":38.9107156,"lon":-94.3821295},"KeJones":{"player_code_id":{"code":"KeJones","id":"Jones, Kelvin","ncaa_id":"4067073"},"number":"43","pos":"C","height":"6-11","height_in":83,"year_class":"Sr","gp":28,"origin":"Chihuahua, Mexico"},"AnJones":{"player_code_id":{"code":"AnJones","id":"Jones, Antwann","ncaa_id":"4396634"},"number":"0","pos":"G","height":"6-6","height_in":78,"year_class":"So","gp":0,"origin":"Orlando, FL","lat":28.5421109,"lon":-81.3790304}}