{"BrGreenlee":{"player_code_id":{"code":"BrGreenlee","id":"Greenlee, Bryan","ncaa_id":"4592701"},"number":"3","pos":"G","height":"6-0","height_in":72,"year_class":"Fr","gp":19,"origin":"Gainesville, FL","lat":29.6519684,"lon":-82.3249846},"MaCarr":{"player_code_id":{"code":"MaCarr","id":"Carr, Marcus","ncaa_id":"4278014"},"number":"5","pos":"G","height":"6-1","height_in":73,"year_class":"So","gp":31,"origin":"Toronto, ON","lat":39.75946455,"lon":-87.50111485527069},"BrRudrud":{"player_code_id":{"code":"BrRudrud","id":"Rudrud, Brady","ncaa_id":"4066386"},"number":"10","pos":"G","height":"6-3","height_in":75,"year_class":"Sr","gp":4,"origin":"Eden Prairie, MN","lat":44.8546856,"lon":-93.470786},"GaKalscheur":{"player_code_id":{"code":"GaKalscheur","id":"Kalscheur, Gabe","ncaa_id":"4397214"},"number":"22","pos":"G","height":"6-4","height_in":76,"year_class":"So","gp":31,"origin":"Edina, MN","lat":44.8897027,"lon":-93.3501222},"AlDemir":{"player_code_id":{"code":"AlDemir","id":"Demir, Alihan","ncaa_id":"4279197"},"number":"30","pos":"F","height":"6-9","height_in":81,"year_class":"Sr","gp":31,"origin":"Ankara, Turkey"},"MiHurt":{"player_code_id":{"code":"MiHurt","id":"Hurt, Michael","ncaa_id":"4066389"},"number":"42","pos":"F","height":"6-7","height_in":79,"year_class":"Sr","gp":25,"origin":"Rochester, MN","lat":44.0234387,"lon":-92.4630182},"TrWilliams":{"player_code_id":{"code":"TrWilliams","id":"Williams, Tre'","ncaa_id":"4432873"},"number":"1","pos":"G","height":"6-5","height_in":77,"year_class":"Fr","gp":31,"origin":"Dallas, TX","lat":32.7762719,"lon":-96.7968559},"DaOturu":{"player_code_id":{"code":"DaOturu","id":"Oturu, Daniel","ncaa_id":"4397215"},"number":"25","pos":"C","height":"6-10","height_in":82,"year_class":"So","gp":31,"origin":"Woodbury, MN","lat":44.919896,"lon":-92.9339449},"PaWillis":{"player_code_id":{"code":"PaWillis","id":"Willis, Payton","ncaa_id":"4066230"},"number":"0","pos":"G","height":"6-4","height_in":76,"year_class":"Jr","gp":27,"origin":"Fayetteville, AR","lat":36.0625843,"lon":-94.1574328},"SaFreeman":{"player_code_id":{"code":"SaFreeman","id":"Freeman, Sam","ncaa_id":"4431771"},"number":"32","pos":"C","height":"6-10","height_in":82,"year_class":"Fr","gp":8,"origin":"Dallas, TX","lat":32.7762719,"lon":-96.7968559},"JaOmersa":{"player_code_id":{"code":"JaOmersa","id":"Omersa, Jarvis","ncaa_id":"4397213"},"number":"21","pos":"F","height":"6-6","height_in":78,"year_class":"So","gp":31,"origin":"Orono, MN","lat":44.9713519,"lon":-93.6044033},"HuConroy":{"player_code_id":{"code":"HuConroy","id":"Conroy, Hunt","ncaa_id":"4277965"},"number":"13","pos":"G","height":"5-10","height_in":70,"year_class":"Jr","gp":2,"origin":"New Orleans, LA","lat":29.9759983,"lon":-90.0782127},"IsIhnen":{"player_code_id":{"code":"IsIhnen","id":"Ihnen, Isaiah","ncaa_id":"4592702"},"number":"35","pos":"F","height":"6-9","height_in":81,"year_class":"Fr","gp":21,"origin":"Boeblingen, Germany"},"ErCurry":{"player_code_id":{"code":"ErCurry","id":"Curry, Eric","ncaa_id":"4066388"},"number":"24","pos":"F","height":"6-9","height_in":81,"year_class":"Jr","gp":0,"origin":"Memphis, TN","lat":35.1460249,"lon":-90.0517638}}