{"JaEllis":{"player_code_id":{"code":"JaEllis","id":"Ellis, Jaden","ncaa_id":"7949243"},"number":"3","pos":"G","height":"6-0","height_in":72,"year_class":"So","gp":12,"origin":"Greensboro, NC"},"JaCross":{"player_code_id":{"code":"JaCross","id":"Cross, Jared","ncaa_id":"7072866"},"number":"24","pos":"G","height":"6-3","height_in":75,"year_class":"Sr","gp":26,"origin":"Leesburg, VA"},"ZaLezanic":{"player_code_id":{"code":"ZaLezanic","id":"Lezanic, Zach","ncaa_id":"7072864"},"number":"10","pos":"G","height":"6-0","height_in":72,"year_class":"Sr","gp":5,"origin":"Berwyn, PA"},"JtDougherty":{"player_code_id":{"code":"JtDougherty","id":"Dougherty, JT","ncaa_id":"7685564"},"number":"33","pos":"F","height":"6-9","height_in":81,"year_class":"Jr","gp":0,"origin":"River Falls, WI"},"BlBarker":{"player_code_id":{"code":"BlBarker","id":"Barker, Blake","ncaa_id":"7495879"},"number":"31","pos":"G","height":"6-2","height_in":74,"year_class":"Jr","gp":25,"origin":"Columbus, IN"},"GrLamb":{"player_code_id":{"code":"GrLamb","id":"Lamb, Griff","ncaa_id":"7685562"},"number":"5","pos":"F","height":"6-8","height_in":80,"year_class":"Jr","gp":1,"origin":"Holbrook, AZ"},"TaLaczkowski":{"player_code_id":{"code":"TaLaczkowski","id":"Laczkowski, Tate","ncaa_id":"8381276"},"number":"32","pos":"F","height":"6-8","height_in":80,"year_class":"Fr","gp":3,"origin":"Dallas, TX"},"AbJohnson":{"player_code_id":{"code":"AbJohnson","id":"Johnson, Abe","ncaa_id":"7378765"},"number":"54","pos":"F","height":"6-8","height_in":80,"year_class":"Sr","gp":31,"origin":"Missoula, MT"},"JoScovens":{"player_code_id":{"code":"JoScovens","id":"Scovens, Josh","ncaa_id":"8381272"},"number":"4","pos":"F","height":"6-4","height_in":76,"year_class":"Fr","gp":32,"origin":"Greensboro, NC"},"TjSmall":{"player_code_id":{"code":"TjSmall","id":"Small, TJ","ncaa_id":"7495894"},"number":"35","pos":"G","height":"6-2","height_in":74,"year_class":"Jr","gp":30,"origin":"Kenner, LA"},"__coach__":{"player_code_id":{"code":"__coach__","id":"Kevin Kuwik"},"number":"","pos":"","height":"","year_class":"","gp":-1},"JaMayo":{"player_code_id":{"code":"JaMayo","id":"Mayo, Jackson","ncaa_id":"8175078"},"number":"21","pos":"G","height":"6-0","height_in":72,"year_class":"So","gp":3,"origin":"Mililani, HI"},"ChPeterson":{"player_code_id":{"code":"ChPeterson","id":"Peterson, Charlie","ncaa_id":"7072867"},"number":"34","pos":"F","height":"6-9","height_in":81,"year_class":"Sr","gp":32,"origin":"Indianapolis, IN"},"BlStClair":{"player_code_id":{"code":"BlStClair","id":"St. Clair, Blane","ncaa_id":"7495877"},"number":"12","pos":"G","height":"6-5","height_in":77,"year_class":"Jr","gp":3,"origin":"Boone, NC"},"KwDavis":{"player_code_id":{"code":"KwDavis","id":"Davis, Kwabena","ncaa_id":"7072865"},"number":"22","pos":"G","height":"6-3","height_in":75,"year_class":"Sr","gp":22,"origin":"San Antonio, TX"},"AjAllenspach":{"player_code_id":{"code":"AjAllenspach","id":"Allenspach, AJ","ncaa_id":"7495883"},"number":"55","pos":"F","height":"6-8","height_in":80,"year_class":"Jr","gp":31,"origin":"Simpsonville, SC"},"ChPerkins":{"player_code_id":{"code":"ChPerkins","id":"Perkins, Chanse","ncaa_id":"7949247"},"number":"25","pos":"F","height":"6-4","height_in":76,"year_class":"So","gp":2,"origin":"Houston, TX"},"KeHailey":{"player_code_id":{"code":"KeHailey","id":"Hailey, Kendall","ncaa_id":"8381274"},"number":"13","pos":"G","height":"6-3","height_in":75,"year_class":"Fr","gp":19,"origin":"Los Angeles, CA"},"DyBlair":{"player_code_id":{"code":"DyBlair","id":"Blair, Dylan","ncaa_id":"8381275"},"number":"23","pos":"G","height":"5-9","height_in":69,"year_class":"Fr","gp":29,"origin":"Downington, PA"},"NoNaess":{"player_code_id":{"code":"NoNaess","id":"Naess, Nolan","ncaa_id":"7495882"},"number":"41","pos":"F","height":"6-8","height_in":80,"year_class":"Jr","gp":1,"origin":"Laguna Beach, CA"},"RyCurry":{"player_code_id":{"code":"RyCurry","id":"Curry, Ryan","ncaa_id":"8381270"},"number":"2","pos":"G","height":"6-0","height_in":72,"year_class":"Fr","gp":32,"origin":"Montgomery, NJ"},"ZaRocco":{"player_code_id":{"code":"ZaRocco","id":"Rocco, Zach","ncaa_id":"8181529"},"number":"14","pos":"G","height":"6-1","height_in":73,"year_class":"Sr","gp":7,"origin":"Export, PA"},"IsCaldwell":{"player_code_id":{"code":"IsCaldwell","id":"Caldwell, Isaiah","ncaa_id":"7495852"},"number":"0","pos":"G","height":"6-4","height_in":76,"year_class":"Jr","gp":22,"origin":"Columbia, SC"},"LuBenson":{"player_code_id":{"code":"LuBenson","id":"Benson, Luke","ncaa_id":"7685566"},"number":"42","pos":"G","height":"5-11","height_in":71,"year_class":"Jr","gp":2,"origin":"Atlanta, GA"},"MaDove":{"player_code_id":{"code":"MaDove","id":"Dove, Matt","ncaa_id":"7072869"},"number":"44","pos":"F","height":"6-10","height_in":82,"year_class":"Sr","gp":24,"origin":"Princeton, IN"},"JoEverson":{"player_code_id":{"code":"JoEverson","id":"Everson, Jorn","ncaa_id":"7949244"},"number":"15","pos":"F","height":"6-8","height_in":80,"year_class":"So","gp":13,"origin":"Williston, ND"}}
