{"BrWalker":{"player_code_id":{"code":"BrWalker","id":"Walker, Bryce","ncaa_id":"5185256"},"number":"42","pos":"G","height":"6-2","height_in":74,"year_class":"Jr","gp":7,"origin":"Beltsville, MD","lat":39.039773499999995,"lon":-76.92718505662606},"ReBeekman":{"player_code_id":{"code":"ReBeekman","id":"Beekman, Reece","ncaa_id":"4432187"},"number":"2","pos":"G","height":"6-3","height_in":75,"year_class":"Sr","gp":34,"origin":"Milwaukee, WI","lat":43.0386475,"lon":-87.9090751},"TaMurray":{"player_code_id":{"code":"TaMurray","id":"Murray, Taine","ncaa_id":"4692906"},"number":"10","pos":"G","height":"6-5","height_in":77,"year_class":"Jr","gp":33,"origin":"Auckland, New Zealand"},"JaGroves":{"player_code_id":{"code":"JaGroves","id":"Groves, Jacob","ncaa_id":"4592583"},"number":"34","pos":"G","height":"6-9","height_in":81,"year_class":"Sr","gp":34,"origin":"Spokane, WA","lat":47.6571934,"lon":-117.42351},"RyDunn":{"player_code_id":{"code":"RyDunn","id":"Dunn, Ryan","ncaa_id":"4888725"},"number":"13","pos":"G","height":"6-8","height_in":80,"year_class":"So","gp":34,"origin":"Freeport, NY","lat":40.6576071,"lon":-73.5835826},"IsMckneely":{"player_code_id":{"code":"IsMckneely","id":"McKneely, Isaac","ncaa_id":"4712845"},"number":"11","pos":"G","height":"6-4","height_in":76,"year_class":"So","gp":33,"origin":"Poca, WV","lat":38.4723137,"lon":-81.8142977},"DaHarris":{"player_code_id":{"code":"DaHarris","id":"Harris, Dante","ncaa_id":"4596531"},"number":"1","pos":"G","height":"6-0","height_in":72,"year_class":"Jr","gp":24,"origin":"Washington, DC","lat":38.8950368,"lon":-77.0365427},"ElGertrude":{"player_code_id":{"code":"ElGertrude","id":"Gertrude, Elijah","ncaa_id":"5080790"},"number":"12","pos":"G","height":"6-4","height_in":76,"year_class":"Fr","gp":16,"origin":"Jersey City, NJ","lat":40.7215682,"lon":-74.047455},"__coach__":{"player_code_id":{"code":"__coach__","id":"Tony Bennett"},"number":"","pos":"","height":"","year_class":"","gp":-1},"BlBuchanan":{"player_code_id":{"code":"BlBuchanan","id":"Buchanan, Blake","ncaa_id":"5079838"},"number":"0","pos":"F","height":"6-11","height_in":83,"year_class":"Fr","gp":34,"origin":"Coeur D Alene, ID","lat":47.6742994,"lon":-116.7811531},"ChBliss":{"player_code_id":{"code":"ChBliss","id":"Bliss, Christian","ncaa_id":"5142618"},"number":"30","pos":"G","height":"6-4","height_in":76,"year_class":"Fr","gp":0,"origin":"Whitestone, NY","lat":40.7135078,"lon":-73.8283132},"DeRoberts":{"player_code_id":{"code":"DeRoberts","id":"Roberts, Desmond","ncaa_id":"5174572"},"number":"5","pos":"G","height":"6-4","height_in":76,"year_class":"Fr","gp":0,"origin":"Charlottesville, VA","lat":38.029306,"lon":-78.4766781},"AnRobinson":{"player_code_id":{"code":"AnRobinson","id":"Robinson, Anthony","ncaa_id":"5143921"},"number":"21","pos":"F","height":"6-10","height_in":82,"year_class":"Fr","gp":0,"origin":"Peachtree City, GA","lat":33.3975472,"lon":-84.5898256},"AnRohde":{"player_code_id":{"code":"AnRohde","id":"Rohde, Andrew","ncaa_id":"5109019"},"number":"4","pos":"G","height":"6-6","height_in":78,"year_class":"So","gp":33,"origin":"Milwaukee, WI","lat":43.0386475,"lon":-87.9090751},"LeBond":{"player_code_id":{"code":"LeBond","id":"Bond III, Leon","ncaa_id":"4838704"},"number":"35","pos":"G","height":"6-5","height_in":77,"year_class":"Fr","gp":24,"origin":"Wauwatosa, WI","lat":43.0494122,"lon":-88.0079271},"TrHow":{"player_code_id":{"code":"TrHow","id":"How, Tristan","ncaa_id":"5105408"},"number":"24","pos":"F","height":"6-7","height_in":79,"year_class":"Sr","gp":9,"origin":"Virginia Beach, VA","lat":36.8496579,"lon":-75.9760751},"JoMinor":{"player_code_id":{"code":"JoMinor","id":"Minor, Jordan","ncaa_id":"4594263"},"number":"22","pos":"F","height":"6-8","height_in":80,"year_class":"Sr","gp":32,"origin":"Kingston, MA","lat":41.9945473,"lon":-70.7244822}}