{"EmBuyukhanli":{"player_code_id":{"code":"EmBuyukhanli","id":"Buyukhanli, Emir","ncaa_id":"4898240"},"number":"11","pos":"G","height":"6-5","height_in":77,"year_class":"Jr","gp":8,"origin":"Ankara, Turkey"},"JaMolloy":{"player_code_id":{"code":"JaMolloy","id":"Molloy, Jack","ncaa_id":"4898244"},"number":"33","pos":"F","height":"6-8","height_in":80,"year_class":"Jr","gp":18,"origin":"Greenwich, CT","lat":41.0264862,"lon":-73.6284598},"DeArlington":{"player_code_id":{"code":"DeArlington","id":"Arlington, Devon","ncaa_id":"5107175"},"number":"44","pos":"G","height":"6-3","height_in":75,"year_class":"So","gp":7,"origin":"San Marcos, CA","lat":33.1352995,"lon":-117.1743395},"AuMahoney":{"player_code_id":{"code":"AuMahoney","id":"Mahoney, August","ncaa_id":"4593361"},"number":"3","pos":"G","height":"6-4","height_in":76,"year_class":"Sr","gp":33,"origin":"Saratoga Springs, NY","lat":43.0821793,"lon":-73.7853915},"MaKnowling":{"player_code_id":{"code":"MaKnowling","id":"Knowling, Matt","ncaa_id":"4898246"},"number":"22","pos":"F","height":"6-6","height_in":78,"year_class":"Sr","gp":28,"origin":"Ellington, CT","lat":41.7834017,"lon":-72.5231973},"LuKolaja":{"player_code_id":{"code":"LuKolaja","id":"Kolaja, Luke","ncaa_id":"4898245"},"number":"21","pos":"F","height":"6-8","height_in":80,"year_class":"Sr","gp":2,"origin":"Montclair, NJ","lat":40.8164458,"lon":-74.2210643},"__coach__":{"player_code_id":{"code":"__coach__","id":"James Jones"},"number":"","pos":"","height":"","year_class":"","gp":-1},"TrMullin":{"player_code_id":{"code":"TrMullin","id":"Mullin, Trevor","ncaa_id":"5177185"},"number":"0","pos":"G","height":"6-0","height_in":72,"year_class":"Fr","gp":10,"origin":"Wellesley, MA","lat":42.2964859,"lon":-71.2925571},"CaSimmons":{"player_code_id":{"code":"CaSimmons","id":"Simmons, Casey","ncaa_id":"4432692"},"number":"14","pos":"G","height":"6-6","height_in":78,"year_class":"So","gp":32,"origin":"Milton, MA","lat":42.2501425,"lon":-71.065573},"DaWolf":{"player_code_id":{"code":"DaWolf","id":"Wolf, Danny","ncaa_id":"5107173"},"number":"1","pos":"F","height":"7-0","height_in":84,"year_class":"So","gp":32,"origin":"Glencoe, IL","lat":42.1350268,"lon":-87.7581188},"YaGharram":{"player_code_id":{"code":"YaGharram","id":"Gharram, Yassine","ncaa_id":"4898248"},"number":"24","pos":"G","height":"6-3","height_in":75,"year_class":"Jr","gp":33,"origin":"San Diego, CA","lat":32.7174202,"lon":-117.162772},"BeMbeng":{"player_code_id":{"code":"BeMbeng","id":"Mbeng, Bez","ncaa_id":"4898237"},"number":"2","pos":"G","height":"6-4","height_in":76,"year_class":"Jr","gp":33,"origin":"Potomac, MD","lat":39.0180508,"lon":-77.1956331355745},"SaAletan":{"player_code_id":{"code":"SaAletan","id":"Aletan, Samson","ncaa_id":"5177187"},"number":"10","pos":"C","height":"6-10","height_in":82,"year_class":"Fr","gp":21,"origin":"Dallas, TX","lat":32.7762719,"lon":-96.7968559},"YuBasa-ama":{"player_code_id":{"code":"YuBasa-ama","id":"Basa-Ama, Yussif","ncaa_id":"4898247"},"number":"23","pos":"F","height":"6-9","height_in":81,"year_class":"Sr","gp":14,"origin":"Bolgatanga, Ghana"},"NiTownsend":{"player_code_id":{"code":"NiTownsend","id":"Townsend, Nick","ncaa_id":"5107174"},"number":"42","pos":"F","height":"6-7","height_in":79,"year_class":"So","gp":33,"origin":"Chappaqua, NY","lat":41.157284000000004,"lon":-73.76769980526316},"JeBasima":{"player_code_id":{"code":"JeBasima","id":"Basima, Jeannot","ncaa_id":"5177186"},"number":"5","pos":"G","height":"6-4","height_in":76,"year_class":"Fr","gp":0,"origin":"Goma, DR Congo"},"TeRice":{"player_code_id":{"code":"TeRice","id":"Rice, Teo","ncaa_id":"4898241"},"number":"12","pos":"G","height":"6-2","height_in":74,"year_class":"Jr","gp":11,"origin":"Bethesda, MD","lat":38.98127255,"lon":-77.12335871396549},"JoPoulakidas":{"player_code_id":{"code":"JoPoulakidas","id":"Poulakidas, John","ncaa_id":"4898238"},"number":"4","pos":"G","height":"6-5","height_in":77,"year_class":"Jr","gp":33,"origin":"Naperville, IL","lat":41.7728699,"lon":-88.1479278}}