{"DaTobiloba":{"player_code_id":{"code":"DaTobiloba","id":"Tobiloba, Daniel","ncaa_id":"9337206"},"number":"34","pos":"C","height":"7-0","height_in":84,"year_class":"Jr","gp":0,"origin":"Lagos, Nigeria"},"__coach__":{"player_code_id":{"code":"__coach__","id":"Bryan Hodgson"},"number":"","pos":"","height":"","year_class":"","gp":-1},"CjBrown":{"player_code_id":{"code":"CjBrown","id":"Brown, CJ","ncaa_id":"5183925"},"number":"11","pos":"F","height":"6-2","height_in":74,"year_class":"So","gp":0,"origin":"Marietta, GA"},"KaWright":{"player_code_id":{"code":"KaWright","id":"Wright, Kameren","ncaa_id":"5313561"},"number":"7","pos":"F","height":"6-6","height_in":78,"year_class":"So","gp":0,"origin":"Gainesville, FL"},"KyO'hare":{"player_code_id":{"code":"KyO'hare","id":"O'Hare, Kyle","ncaa_id":"9337209"},"number":"22","pos":"F","height":"6-7","height_in":79,"year_class":"Jr","gp":0,"origin":"Tampa, FL"},"JaReid":{"player_code_id":{"code":"JaReid","id":"Reid, Jayden","ncaa_id":"5107222"},"number":"0","pos":"G","height":"5-10","height_in":70,"year_class":"Jr","gp":0,"origin":"Westbury, NY"},"DeGreen":{"player_code_id":{"code":"DeGreen","id":"Green, De'Ante","ncaa_id":"4684795"},"number":"1","pos":"F","height":"6-10","height_in":82,"year_class":"Sr","gp":0,"origin":"Asheville, NC"}}